artefacts/__init__.py
artefacts/api.py
artefacts/config.py
artefacts/conftest.py
artefacts/deserializers.py
artefacts/loaders.py
artefacts/mixins.py
artefacts/models.py
artefacts/state.py
artefacts/version.py
artefacts-1.2.0.dist-info/LICENSE
artefacts-1.2.0.dist-info/WHEEL
artefacts-1.2.0.dist-info/METADATA
artefacts-1.2.0.dist-info/RECORD
