Metadata-Version: 2.1
Name: artefacts
Version: 1.2.0
Summary: Deserialization for dbt artifacts
Author: Tom Waterman
Author-email: tjwaterman99@gmail.com
Requires-Python: >=3.7,<4.0
Classifier: Programming Language :: Python :: 3
Classifier: Programming Language :: Python :: 3.10
Classifier: Programming Language :: Python :: 3.7
Classifier: Programming Language :: Python :: 3.8
Classifier: Programming Language :: Python :: 3.9
Requires-Dist: packaging (>=21.3,<22.0)
Requires-Dist: pydantic (>=1.9.0,<2.0.0)
Requires-Dist: toml (>=0.10.2,<0.11.0)
